{"get": "fixtures", "parameters": {"date": "2019-12-24"}, "errors": [], "results": 33, "paging": {"current": 1, "total": 1}, "response": [{"fixture": {"id": 240738, "referee": "O. Nation", "timezone": "UTC", "date": "2019-12-24T01:00:00+00:00", "timestamp": 1577149200, "periods": {"first": 1577149200, "second": 1577152800}, "venue": {"id": null, "name": "Waterhouse Stadium", "city": "Kingston"}, "status": {"long": "Match Finished", "short": "FT", "elapsed": 90}}, "league": {"id": 322, "name": "Premier League", "country": "Jamaica", "logo": "https://media.api-sports.io/football/leagues/322.png", "flag": "https://media.api-sports.io/flags/jm.svg", "season": 2019, "round": "Regular Season - 19"}, "teams": {"home": {"id": 3447, "name": "Waterhouse", "logo": "https://media.api-sports.io/football/teams/3447.png", "winner": false}, "away": {"id": 6407, "name": "Molynes United", "logo": "https://media.api-sports.io/football/teams/6407.png", "winner": true}}, "goals": {"home": 1, "away": 2}, "score": {"halftime": {"home": 0, "away": 1}, "fulltime": {"home": 1, "away": 2}, "extratime": {"home": null, "away": null}, "penalty": {"home": null, "away": null}}}, {"fixture": {"id": 464545, "referee": null, "timezone": "UTC", "date": "2019-12-24T07:00:00+00:00", "timestamp": 1577170800, "periods": {"first": 1577170800, "second": 1577174400}, "venue": {"id": 7773, "name": "Sokoine Stadium", "city": "Mbeya"}, "status": {"long": "Match Finished", "short": "FT", "elapsed": 90}}, "league": {"id": 567, "name": "Ligi kuu Bara", "country": "Tanzania", "logo": "https://media.api-sports.io/football/leagues/567.png", "flag": "https://media.api-sports.io/flags/tz.svg", "season": 2019, "round": "Regular Season - 13"}, "teams": {"home": {"id": 12194, "name": "Mbeya City", "logo": "https://media.api-sports.io/football/teams/12194.png", "winner": null}, "away": {"id": 5370, "name": "Young Africans", "logo": "https://media.api-sports.io/football/teams/5370.png", "winner": null}}, "goals": {"home": 0, "away": 0}, "score": {"halftime": {"home": null, "away": null}, "fulltime": {"home": 0, "away": 0}, "extratime": {"home": null, "away": null}, "penalty": {"home": null, "away": null}}}, {"fixture": {"id": 246971, "referee": "R. Adel", "timezone": "UTC", "date": "2019-12-24T11:00:00+00:00", "timestamp": 1577185200, "periods": {"first": 1577185200, "second": 1577188800}, "venue": {"id": 1889, "name": "Takhti Stadium", "city": "Jam"}, "status": {"long": "Match Finished", "short": "FT", "elapsed": 90}}, "league": {"id": 290, "name": "Persian Gulf Pro League", "country": "Iran", "logo": "https://media.api-sports.io/football/leagues/290.png", "flag": "https://media.api-sports.io/flags/ir.svg", "season": 2019, "round": "Regular Season - 11"}, "teams": {"home": {"id": 2702, "name": "Pars Jonoubi JAM", "logo": "https://media.api-sports.io/football/teams/2702.png", "winner": true}, "away": {"id": 2741, "name": "Paykan", "logo": "https://media.api-sports.io/football/teams/2741.png", "winner": false}}, "goals": {"home": 3, "away": 1}, "score": {"halftime": {"home": 2, "away": 0}, "fulltime": {"home": 3, "away": 1}, "extratime": {"home": null, "away": null}, "penalty": {"home": null, "away": null}}}, {"fixture": {"id": 246968, "referee": "M. Akbarian", "timezone": "UTC", "date": "2019-12-24T11:30:00+00:00", "timestamp": 1577187000, "periods": {"first": 1577187000, "second": 1577190600}, "venue": {"id": 847, "name": "Imam Ali Stadium", "city": "Sirjan"}, "status": {"long": "Match Finished", "short": "FT", "elapsed": 90}}, "league": {"id": 290, "name": "Persian Gulf Pro League", "country": "Iran", "logo": "https://media.api-sports.io/football/leagues/290.png", "flag": "https://media.api-sports.io/flags/ir.svg", "season": 2019, "round": "Regular Season - 11"}, "teams": {"home": {"id": 2714, "name": "Gol Gohar", "logo": "https://media.api-sports.io/football/teams/2714.png", "winner": true}, "away": {"id": 2720, "name": "Machine Sazi FC", "logo": "https://media.api-sports.io/football/teams/2720.png", "winner": false}}, "goals": {"home": 1, "away": 0}, "score": {"halftime": {"home": 0, "away": 0}, "fulltime": {"home": 1, "away": 0}, "extratime": {"home": null, "away": null}, "penalty": {"home": null, "away": null}}}, {"fixture": {"id": 234567, "referee": null, "timezone": "UTC", "date": "2019-12-24T11:55:00+00:00", "timestamp": 1577188500, "periods": {"first": 1577188500, "second": 1577192100}, "venue": {"id": 1376, "name": "Prince Saud bin Jalawi Stadium", "city": "Khobar"}, "status": {"long": "Match Finished", "short": "FT", "elapsed": 90}}, "league": {"id": 308, "name": "Division 1", "country": "Saudi-Arabia", "logo": "https://media.api-sports.io/football/leagues/308.png", "flag": "https://media.api-sports.io/flags/sa.svg", "season": 2019, "round": "Regular Season - 18"}, "teams": {"home": {"id": 2933, "name": "Al-Qadisiyah FC", "logo": "https://media.api-sports.io/football/teams/2933.png", "winner": false}, "away": {"id": 2942, "name": "Al Taee", "logo": "https://media.api-sports.io/football/teams/2942.png", "winner": true}}, "goals": {"home": 0, "away": 1}, "score": {"halftime": {"home": null, "away": null}, "fulltime": {"home": 0, "away": 1}, "extratime": {"home": null, "away": null}, "penalty": {"home": null, "away": null}}}, {"fixture": {"id": 246973, "referee": "H. Haj Malek", "timezone": "UTC", "date": "2019-12-24T12:00:00+00:00", "timestamp": 1577188800, "periods": {"first": 1577188800, "second": 1577192400}, "venue": {"id": 860, "name": "Yadegar-e-Emam Stadium", "city": "Tabriz"}, "status": {"long": "Match Finished", "short": "FT", "elapsed": 90}}, "league": {"id": 290, "name": "Persian Gulf Pro League", "country": "Iran", "logo": "https://media.api-sports.io/football/leagues/290.png", "flag": "https://media.api-sports.io/flags/ir.svg", "season": 2019, "round": "Regular Season - 11"}, "teams": {"home": {"id": 2737, "name": "Tractor Sazi", "logo": "https://media.api-sports.io/football/teams/2737.png", "winner": true}, "away": {"id": 2740, "name": "Padideh Khorasan", "logo": "https://media.api-sports.io/football/teams/2740.png", "winner": false}}, "goals": {"home": 3, "away": 1}, "score": {"halftime": {"home": 1, "away": 0}, "fulltime": {"home": 3, "away": 1}, "extratime": {"home": null, "away": null}, "penalty": {"home": null, "away": null}}}, {"fixture": {"id": 234568, "referee": null, "timezone": "UTC", "date": "2019-12-24T12:15:00+00:00", "timestamp": 1577189700, "periods": {"first": 1577189700, "second": 1577193300}, "venue": {"id": 1367, "name": "Al Majma'ah Sports City Stadium", "city": "Al Majma'ah"}, "status": {"long": "Match Finished", "short": "FT", "elapsed": 90}}, "league": {"id": 308, "name": "Division 1", "country": "Saudi-Arabia", "logo": "https://media.api-sports.io/football/leagues/308.png", "flag": "https://media.api-sports.io/flags/sa.svg", "season": 2019, "round": "Regular Season - 18"}, "teams": {"home": {"id": 2952, "name": "Al Mojzel", "logo": "https://media.api-sports.io/football/teams/2952.png", "winner": true}, "away": {"id": 2927, "name": "Najran", "logo": "https://media.api-sports.io/football/teams/2927.png", "winner": false}}, "goals": {"home": 3, "away": 1}, "score": {"halftime": {"home": null, "away": null}, "fulltime": {"home": 3, "away": 1}, "extratime": {"home": null, "away": null}, "penalty": {"home": null, "away": null}}}, {"fixture": {"id": 234569, "referee": null, "timezone": "UTC", "date": "2019-12-24T12:20:00+00:00", "timestamp": 1577190000, "periods": {"first": 1577190000, "second": 1577193600}, "venue": {"id": 4629, "name": "Al-Amal Club Stadium", "city": "Al Bukayriyah"}, "status": {"long": "Match Finished", "short": "FT", "elapsed": 90}}, "league": {"id": 308, "name": "Division 1", "country": "Saudi-Arabia", "logo": "https://media.api-sports.io/football/leagues/308.png", "flag": "https://media.api-sports.io/flags/sa.svg", "season": 2019, "round": "Regular Season - 18"}, "teams": {"home": {"id": 2966, "name": "Al Bukayriyah", "logo": "https://media.api-sports.io/football/teams/2966.png", "winner": false}, "away": {"id": 6258, "name": "Hottain", "logo": "https://media.api-sports.io/football/teams/6258.png", "winner": true}}, "goals": {"home": 0, "away": 1}, "score": {"halftime": {"home": null, "away": null}, "fulltime": {"home": 0, "away": 1}, "extratime": {"home": null, "away": null}, "penalty": {"home": null, "away": null}}}, {"fixture": {"id": 244640, "referee": "Mahmoud El Banna", "timezone": "UTC", "date": "2019-12-24T12:30:00+00:00", "timestamp": 1577190600, "periods": {"first": 1577190600, "second": 1577194200}, "venue": {"id": 2686, "name": "Tanta Stadium", "city": "Tanta"}, "status": {"long": "Match Finished", "short": "FT", "elapsed": 90}}, "league": {"id": 233, "name": "Premier League", "country": "Egypt", "logo": "https://media.api-sports.io/football/leagues/233.png", "flag": "https://media.api-sports.io/flags/eg.svg", "season": 2019, "round": "Regular Season - 10"}, "teams": {"home": {"id": 1045, "name": "Tanta SC", "logo": "https://media.api-sports.io/football/teams/1045.png", "winner": null}, "away": {"id": 1048, "name": "Aswan Sc", "logo": "https://media.api-sports.io/football/teams/1048.png", "winner": null}}, "goals": {"home": 2, "away": 2}, "score": {"halftime": {"home": 0, "away": 1}, "fulltime": {"home": 2, "away": 2}, "extratime": {"home": null, "away": null}, "penalty": {"home": null, "away": null}}}, {"fixture": {"id": 335996, "referee": "B. Gassama", "timezone": "UTC", "date": "2019-12-24T12:40:00+00:00", "timestamp": 1577191200, "periods": {"first": 1577191200, "second": 1577194800}, "venue": {"id": 1362, "name": "Prince Sultan bin Abdul Aziz Stadium", "city": "Abha"}, "status": {"long": "Match Finished", "short": "FT", "elapsed": 90}}, "league": {"id": 504, "name": "King's Cup", "country": "Saudi-Arabia", "logo": "https://media.api-sports.io/football/leagues/504.png", "flag": "https://media.api-sports.io/flags/sa.svg", "season": 2020, "round": "8th Finals"}, "teams": {"home": {"id": 2956, "name": "Dhamk", "logo": "https://media.api-sports.io/football/teams/2956.png", "winner": false}, "away": {"id": 2939, "name": "Al-Nassr", "logo": "https://media.api-sports.io/football/teams/2939.png", "winner": true}}, "goals": {"home": 2, "away": 4}, "score": {"halftime": {"home": 2, "away": 1}, "fulltime": {"home": 2, "away": 4}, "extratime": {"home": null, "away": null}, "penalty": {"home": null, "away": null}}}, {"fixture": {"id": 367340, "referee": null, "timezone": "UTC", "date": "2019-12-24T12:40:00+00:00", "timestamp": 1577191200, "periods": {"first": 1577191200, "second": 1577194800}, "venue": {"id": 6331, "name": "Khalid Bin Mohammed Stadium", "city": "Sharjah"}, "status": {"long": "Match Finished", "short": "FT", "elapsed": 90}}, "league": {"id": 560, "name": "Presidents Cup", "country": "United-Arab-Emirates", "logo": "https://media.api-sports.io/football/leagues/560.png", "flag": "https://media.api-sports.io/flags/ae.svg", "season": 2019, "round": "8th Finals"}, "teams": {"home": {"id": 2876, "name": "Al-Ittihad Kalba", "logo": "https://media.api-sports.io/football/teams/2876.png", "winner": true}, "away": {"id": 9136, "name": "Al Bataeh", "logo": "https://media.api-sports.io/football/teams/9136.png", "winner": false}}, "goals": {"home": 4, "away": 2}, "score": {"halftime": {"home": null, "away": null}, "fulltime": {"home": 4, "away": 2}, "extratime": {"home": null, "away": null}, "penalty": {"home": null, "away": null}}}, {"fixture": {"id": 367341, "referee": null, "timezone": "UTC", "date": "2019-12-24T12:50:00+00:00", "timestamp": 1577191800, "periods": {"first": 1577191800, "second": 1577195400}, "venue": {"id": 1605, "name": "Zabeel Stadium", "city": "Dubai"}, "status": {"long": "Match Finished", "short": "FT", "elapsed": 90}}, "league": {"id": 560, "name": "Presidents Cup", "country": "United-Arab-Emirates", "logo": "https://media.api-sports.io/football/leagues/560.png", "flag": "https://media.api-sports.io/flags/ae.svg", "season": 2019, "round": "8th Finals"}, "teams": {"home": {"id": 10155, "name": "Al Nasr", "logo": "https://media.api-sports.io/football/teams/10155.png", "winner": false}, "away": {"id": 2870, "name": "Shabab Al Ahli Dubai", "logo": "https://media.api-sports.io/football/teams/2870.png", "winner": true}}, "goals": {"home": 1, "away": 2}, "score": {"halftime": {"home": null, "away": null}, "fulltime": {"home": 1, "away": 2}, "extratime": {"home": null, "away": null}, "penalty": {"home": null, "away": null}}}, {"fixture": {"id": 233669, "referee": "R. Guezguez", "timezone": "UTC", "date": "2019-12-24T13:00:00+00:00", "timestamp": 1577192400, "periods": {"first": 1577192400, "second": 1577196000}, "venue": {"id": 1776, "name": "Stade Municipal de M\u00e9tlaoui", "city": "M\u00e9tlaoui"}, "status": {"long": "Match Finished", "short": "FT", "elapsed": 90}}, "league": {"id": 202, "name": "Ligue 1", "country": "Tunisia", "logo": "https://media.api-sports.io/football/leagues/202.png", "flag": "https://media.api-sports.io/flags/tn.svg", "season": 2019, "round": "Regular Season - 12"}, "teams": {"home": {"id": 984, "name": "Etoile S. Metlaoui", "logo": "https://media.api-sports.io/football/teams/984.png", "winner": false}, "away": {"id": 980, "name": "Esperance Tunis", "logo": "https://media.api-sports.io/football/teams/980.png", "winner": true}}, "goals": {"home": 1, "away": 2}, "score": {"halftime": {"home": 1, "away": 0}, "fulltime": {"home": 1, "away": 2}, "extratime": {"home": null, "away": null}, "penalty": {"home": null, "away": null}}}, {"fixture": {"id": 291832, "referee": null, "timezone": "UTC", "date": "2019-12-24T13:00:00+00:00", "timestamp": 1577192400, "periods": {"first": 1577192400, "second": 1577196000}, "venue": {"id": null, "name": "Alnagea Staduim", "city": "Al Fashir"}, "status": {"long": "Match Finished", "short": "FT", "elapsed": 90}}, "league": {"id": 402, "name": "Sudani Premier League", "country": "Sudan", "logo": "https://media.api-sports.io/football/leagues/402.png", "flag": "https://media.api-sports.io/flags/sd.svg", "season": 2019, "round": "Regular Season - 15"}, "teams": {"home": {"id": 5551, "name": "Hilal El-Fasher", "logo": "https://media.api-sports.io/football/teams/5551.png", "winner": true}, "away": {"id": 5235, "name": "Al Ahly Shendi", "logo": "https://media.api-sports.io/football/teams/5235.png", "winner": false}}, "goals": {"home": 1, "away": 0}, "score": {"halftime": {"home": null, "away": null}, "fulltime": {"home": 1, "away": 0}, "extratime": {"home": null, "away": null}, "penalty": {"home": null, "away": null}}}, {"fixture": {"id": 234570, "referee": null, "timezone": "UTC", "date": "2019-12-24T14:40:00+00:00", "timestamp": 1577198400, "periods": {"first": 1577198400, "second": 1577202000}, "venue": {"id": 1363, "name": "Prince Abdullah bin Jalawi Sports City Stadium", "city": "Al-Hasa"}, "status": {"long": "Match Finished", "short": "FT", "elapsed": 90}}, "league": {"id": 308, "name": "Division 1", "country": "Saudi-Arabia", "logo": "https://media.api-sports.io/football/leagues/308.png", "flag": "https://media.api-sports.io/flags/sa.svg", "season": 2019, "round": "Regular Season - 18"}, "teams": {"home": {"id": 2946, "name": "Al Najoom", "logo": "https://media.api-sports.io/football/teams/2946.png", "winner": false}, "away": {"id": 2984, "name": "Al-Thuqbah", "logo": "https://media.api-sports.io/football/teams/2984.png", "winner": true}}, "goals": {"home": 0, "away": 2}, "score": {"halftime": {"home": null, "away": null}, "fulltime": {"home": 0, "away": 2}, "extratime": {"home": null, "away": null}, "penalty": {"home": null, "away": null}}}, {"fixture": {"id": 244644, "referee": "Mohammed Yousef", "timezone": "UTC", "date": "2019-12-24T15:00:00+00:00", "timestamp": 1577199600, "periods": {"first": 1577199600, "second": 1577203200}, "venue": {"id": 481, "name": "Cairo Military Academy Stadium", "city": "Cairo"}, "status": {"long": "Match Finished", "short": "FT", "elapsed": 90}}, "league": {"id": 233, "name": "Premier League", "country": "Egypt", "logo": "https://media.api-sports.io/football/leagues/233.png", "flag": "https://media.api-sports.io/flags/eg.svg", "season": 2019, "round": "Regular Season - 10"}, "teams": {"home": {"id": 7520, "name": "Masr", "logo": "https://media.api-sports.io/football/teams/7520.png", "winner": null}, "away": {"id": 1038, "name": "Misr EL Makasa", "logo": "https://media.api-sports.io/football/teams/1038.png", "winner": null}}, "goals": {"home": 2, "away": 2}, "score": {"halftime": {"home": 1, "away": 0}, "fulltime": {"home": 2, "away": 2}, "extratime": {"home": null, "away": null}, "penalty": {"home": null, "away": null}}}, {"fixture": {"id": 234571, "referee": null, "timezone": "UTC", "date": "2019-12-24T15:05:00+00:00", "timestamp": 1577199900, "periods": {"first": 1577199900, "second": 1577203500}, "venue": {"id": 1371, "name": "Prince Abdul Aziz bin Musa'ed Stadium", "city": "Hail"}, "status": {"long": "Match Finished", "short": "FT", "elapsed": 90}}, "league": {"id": 308, "name": "Division 1", "country": "Saudi-Arabia", "logo": "https://media.api-sports.io/football/leagues/308.png", "flag": "https://media.api-sports.io/flags/sa.svg", "season": 2019, "round": "Regular Season - 18"}, "teams": {"home": {"id": 2958, "name": "Al Jabalain", "logo": "https://media.api-sports.io/football/teams/2958.png", "winner": false}, "away": {"id": 2943, "name": "Ohod", "logo": "https://media.api-sports.io/football/teams/2943.png", "winner": true}}, "goals": {"home": 1, "away": 3}, "score": {"halftime": {"home": null, "away": null}, "fulltime": {"home": 1, "away": 3}, "extratime": {"home": null, "away": null}, "penalty": {"home": null, "away": null}}}, {"fixture": {"id": 367342, "referee": null, "timezone": "UTC", "date": "2019-12-24T15:50:00+00:00", "timestamp": 1577202600, "periods": {"first": 1577202600, "second": 1577206200}, "venue": {"id": null, "name": "Bani Yas Stadium", "city": "Abu Dhabi"}, "status": {"long": "Match Finished", "short": "FT", "elapsed": 90}}, "league": {"id": 560, "name": "Presidents Cup", "country": "United-Arab-Emirates", "logo": "https://media.api-sports.io/football/leagues/560.png", "flag": "https://media.api-sports.io/flags/ae.svg", "season": 2019, "round": "8th Finals"}, "teams": {"home": {"id": 2871, "name": "Al-Jazira", "logo": "https://media.api-sports.io/football/teams/2871.png", "winner": true}, "away": {"id": 2875, "name": "Al Wahda FC", "logo": "https://media.api-sports.io/football/teams/2875.png", "winner": false}}, "goals": {"home": 3, "away": 2}, "score": {"halftime": {"home": null, "away": null}, "fulltime": {"home": 3, "away": 2}, "extratime": {"home": null, "away": null}, "penalty": {"home": null, "away": null}}}, {"fixture": {"id": 367343, "referee": null, "timezone": "UTC", "date": "2019-12-24T15:50:00+00:00", "timestamp": 1577202600, "periods": {"first": 1577202600, "second": 1577206200}, "venue": {"id": null, "name": "Al-Sharjah Stadium", "city": "Sharjah"}, "status": {"long": "Match Finished", "short": "FT", "elapsed": 90}}, "league": {"id": 560, "name": "Presidents Cup", "country": "United-Arab-Emirates", "logo": "https://media.api-sports.io/football/leagues/560.png", "flag": "https://media.api-sports.io/flags/ae.svg", "season": 2019, "round": "8th Finals"}, "teams": {"home": {"id": 2872, "name": "Al-Wasl FC", "logo": "https://media.api-sports.io/football/teams/2872.png", "winner": true}, "away": {"id": 4912, "name": "Khorfakkan", "logo": "https://media.api-sports.io/football/teams/4912.png", "winner": false}}, "goals": {"home": 1, "away": 0}, "score": {"halftime": {"home": null, "away": null}, "fulltime": {"home": 1, "away": 0}, "extratime": {"home": null, "away": null}, "penalty": {"home": null, "away": null}}}, {"fixture": {"id": 292649, "referee": null, "timezone": "UTC", "date": "2019-12-24T16:30:00+00:00", "timestamp": 1577205000, "periods": {"first": 1577205000, "second": 1577208600}, "venue": {"id": 3954, "name": "Khartoum Stadium", "city": "Khartoum"}, "status": {"long": "Match Finished", "short": "FT", "elapsed": 90}}, "league": {"id": 402, "name": "Sudani Premier League", "country": "Sudan", "logo": "https://media.api-sports.io/football/leagues/402.png", "flag": "https://media.api-sports.io/flags/sd.svg", "season": 2019, "round": "Regular Season - 17"}, "teams": {"home": {"id": 5238, "name": "Al Khartoum", "logo": "https://media.api-sports.io/football/teams/5238.png", "winner": true}, "away": {"id": 5236, "name": "Al Hilal Kadougli", "logo": "https://media.api-sports.io/football/teams/5236.png", "winner": false}}, "goals": {"home": 3, "away": 0}, "score": {"halftime": {"home": null, "away": null}, "fulltime": {"home": 3, "away": 0}, "extratime": {"home": null, "away": null}, "penalty": {"home": null, "away": null}}}, {"fixture": {"id": 178259, "referee": "O. Lugasi", "timezone": "UTC", "date": "2019-12-24T17:00:00+00:00", "timestamp": 1577206800, "periods": {"first": 1577206800, "second": 1577210400}, "venue": {"id": 3406, "name": "Lod Municipal Stadium", "city": "Bnei-Lod"}, "status": {"long": "Match Finished", "short": "FT", "elapsed": 90}}, "league": {"id": 382, "name": "Liga Leumit", "country": "Israel", "logo": "https://media.api-sports.io/football/leagues/382.png", "flag": "https://media.api-sports.io/flags/il.svg", "season": 2019, "round": "Regular Season - 16"}, "teams": {"home": {"id": 4485, "name": "Hapoel Bnei Lod", "logo": "https://media.api-sports.io/football/teams/4485.png", "winner": null}, "away": {"id": 4494, "name": "Maccabi Ahi Nazareth", "logo": "https://media.api-sports.io/football/teams/4494.png", "winner": null}}, "goals": {"home": 1, "away": 1}, "score": {"halftime": {"home": 0, "away": 1}, "fulltime": {"home": 1, "away": 1}, "extratime": {"home": null, "away": null}, "penalty": {"home": null, "away": null}}}, {"fixture": {"id": 178261, "referee": "G. Levi", "timezone": "UTC", "date": "2019-12-24T17:00:00+00:00", "timestamp": 1577206800, "periods": {"first": 1577206800, "second": 1577210400}, "venue": {"id": 3415, "name": "Nes Tziona Stadium", "city": "Ness Ziona"}, "status": {"long": "Match Finished", "short": "FT", "elapsed": 90}}, "league": {"id": 382, "name": "Liga Leumit", "country": "Israel", "logo": "https://media.api-sports.io/football/leagues/382.png", "flag": "https://media.api-sports.io/flags/il.svg", "season": 2019, "round": "Regular Season - 16"}, "teams": {"home": {"id": 4480, "name": "Beitar Tel Aviv Ramla", "logo": "https://media.api-sports.io/football/teams/4480.png", "winner": true}, "away": {"id": 4490, "name": "Hapoel Ramat HaSharon", "logo": "https://media.api-sports.io/football/teams/4490.png", "winner": false}}, "goals": {"home": 4, "away": 1}, "score": {"halftime": {"home": 3, "away": 1}, "fulltime": {"home": 4, "away": 1}, "extratime": {"home": null, "away": null}, "penalty": {"home": null, "away": null}}}, {"fixture": {"id": 178262, "referee": "M. Shemesh", "timezone": "UTC", "date": "2019-12-24T17:00:00+00:00", "timestamp": 1577206800, "periods": {"first": 1577206800, "second": 1577210400}, "venue": {"id": 2610, "name": "National Stadium Ramat Gan", "city": "Ramat Gan"}, "status": {"long": "Match Finished", "short": "FT", "elapsed": 90}}, "league": {"id": 382, "name": "Liga Leumit", "country": "Israel", "logo": "https://media.api-sports.io/football/leagues/382.png", "flag": "https://media.api-sports.io/flags/il.svg", "season": 2019, "round": "Regular Season - 16"}, "teams": {"home": {"id": 4489, "name": "Hapoel Ramat Gan", "logo": "https://media.api-sports.io/football/teams/4489.png", "winner": true}, "away": {"id": 4484, "name": "Hapoel Ashkelon", "logo": "https://media.api-sports.io/football/teams/4484.png", "winner": false}}, "goals": {"home": 2, "away": 0}, "score": {"halftime": {"home": 2, "away": 0}, "fulltime": {"home": 2, "away": 0}, "extratime": {"home": null, "away": null}, "penalty": {"home": null, "away": null}}}, {"fixture": {"id": 178263, "referee": "S. Berman", "timezone": "UTC", "date": "2019-12-24T17:00:00+00:00", "timestamp": 1577206800, "periods": {"first": 1577206800, "second": 1577210400}, "venue": {"id": 3402, "name": "Doha Stadium", "city": "Sakhnin"}, "status": {"long": "Match Finished", "short": "FT", "elapsed": 90}}, "league": {"id": 382, "name": "Liga Leumit", "country": "Israel", "logo": "https://media.api-sports.io/football/leagues/382.png", "flag": "https://media.api-sports.io/flags/il.svg", "season": 2019, "round": "Regular Season - 16"}, "teams": {"home": {"id": 4481, "name": "Bnei Sakhnin", "logo": "https://media.api-sports.io/football/teams/4481.png", "winner": null}, "away": {"id": 4492, "name": "Hapoel Umm al-Fahm", "logo": "https://media.api-sports.io/football/teams/4492.png", "winner": null}}, "goals": {"home": 1, "away": 1}, "score": {"halftime": {"home": 1, "away": 1}, "fulltime": {"home": 1, "away": 1}, "extratime": {"home": null, "away": null}, "penalty": {"home": null, "away": null}}}, {"fixture": {"id": 178265, "referee": "R. Geva", "timezone": "UTC", "date": "2019-12-24T17:00:00+00:00", "timestamp": 1577206800, "periods": {"first": 1577206800, "second": 1577210400}, "venue": {"id": 3413, "name": "Ilut Stadium", "city": "Ilut"}, "status": {"long": "Match Finished", "short": "FT", "elapsed": 90}}, "league": {"id": 382, "name": "Liga Leumit", "country": "Israel", "logo": "https://media.api-sports.io/football/leagues/382.png", "flag": "https://media.api-sports.io/flags/il.svg", "season": 2019, "round": "Regular Season - 16"}, "teams": {"home": {"id": 4487, "name": "Hapoel Nazareth Illit", "logo": "https://media.api-sports.io/football/teams/4487.png", "winner": null}, "away": {"id": 4495, "name": "Maccabi Petah Tikva", "logo": "https://media.api-sports.io/football/teams/4495.png", "winner": null}}, "goals": {"home": 1, "away": 1}, "score": {"halftime": {"home": 0, "away": 0}, "fulltime": {"home": 1, "away": 1}, "extratime": {"home": null, "away": null}, "penalty": {"home": null, "away": null}}}, {"fixture": {"id": 178266, "referee": "A. Matmon", "timezone": "UTC", "date": "2019-12-24T17:00:00+00:00", "timestamp": 1577206800, "periods": {"first": 1577206800, "second": 1577210400}, "venue": {"id": 3403, "name": "Acre Municipal Stadium", "city": "Accre"}, "status": {"long": "Match Finished", "short": "FT", "elapsed": 90}}, "league": {"id": 382, "name": "Liga Leumit", "country": "Israel", "logo": "https://media.api-sports.io/football/leagues/382.png", "flag": "https://media.api-sports.io/flags/il.svg", "season": 2019, "round": "Regular Season - 16"}, "teams": {"home": {"id": 4482, "name": "Hapoel Acre", "logo": "https://media.api-sports.io/football/teams/4482.png", "winner": true}, "away": {"id": 4493, "name": "Kafr Qasim", "logo": "https://media.api-sports.io/football/teams/4493.png", "winner": false}}, "goals": {"home": 1, "away": 0}, "score": {"halftime": {"home": 0, "away": 0}, "fulltime": {"home": 1, "away": 0}, "extratime": {"home": null, "away": null}, "penalty": {"home": null, "away": null}}}, {"fixture": {"id": 179369, "referee": "S. Ben Avraham", "timezone": "UTC", "date": "2019-12-24T17:00:00+00:00", "timestamp": 1577206800, "periods": {"first": 1577206800, "second": 1577210400}, "venue": {"id": 3408, "name": "HaMoshava Stadium", "city": "Petach-Tikva"}, "status": {"long": "Match Finished", "short": "FT", "elapsed": 90}}, "league": {"id": 383, "name": "Ligat Ha'al", "country": "Israel", "logo": "https://media.api-sports.io/football/leagues/383.png", "flag": "https://media.api-sports.io/flags/il.svg", "season": 2019, "round": "Regular Season - 15"}, "teams": {"home": {"id": 4497, "name": "Hapoel Kfar Saba", "logo": "https://media.api-sports.io/football/teams/4497.png", "winner": false}, "away": {"id": 4510, "name": "Ironi Kiryat Shmona", "logo": "https://media.api-sports.io/football/teams/4510.png", "winner": true}}, "goals": {"home": 0, "away": 3}, "score": {"halftime": {"home": 0, "away": 1}, "fulltime": {"home": 0, "away": 3}, "extratime": {"home": null, "away": null}, "penalty": {"home": null, "away": null}}}, {"fixture": {"id": 292653, "referee": null, "timezone": "UTC", "date": "2019-12-24T17:00:00+00:00", "timestamp": 1577206800, "periods": {"first": 1577206800, "second": 1577210400}, "venue": {"id": 3962, "name": "Al-Ubayyid Stadium", "city": "Al-Ubayyid"}, "status": {"long": "Match Finished", "short": "FT", "elapsed": 90}}, "league": {"id": 402, "name": "Sudani Premier League", "country": "Sudan", "logo": "https://media.api-sports.io/football/leagues/402.png", "flag": "https://media.api-sports.io/flags/sd.svg", "season": 2019, "round": "Regular Season - 17"}, "teams": {"home": {"id": 5247, "name": "Hilal Obayed", "logo": "https://media.api-sports.io/football/teams/5247.png", "winner": true}, "away": {"id": 5241, "name": "Al Rabta Kosti", "logo": "https://media.api-sports.io/football/teams/5241.png", "winner": false}}, "goals": {"home": 3, "away": 0}, "score": {"halftime": {"home": null, "away": null}, "fulltime": {"home": 3, "away": 0}, "extratime": {"home": null, "away": null}, "penalty": {"home": null, "away": null}}}, {"fixture": {"id": 179366, "referee": "A. Shiloach", "timezone": "UTC", "date": "2019-12-24T17:30:00+00:00", "timestamp": 1577208600, "periods": {"first": 1577208600, "second": 1577212200}, "venue": {"id": 869, "name": "Winner Stadium", "city": "Netanya"}, "status": {"long": "Match Finished", "short": "FT", "elapsed": 90}}, "league": {"id": 383, "name": "Ligat Ha'al", "country": "Israel", "logo": "https://media.api-sports.io/football/leagues/383.png", "flag": "https://media.api-sports.io/flags/il.svg", "season": 2019, "round": "Regular Season - 15"}, "teams": {"home": {"id": 4500, "name": "Hapoel Hadera", "logo": "https://media.api-sports.io/football/teams/4500.png", "winner": false}, "away": {"id": 563, "name": "Hapoel Beer Sheva", "logo": "https://media.api-sports.io/football/teams/563.png", "winner": true}}, "goals": {"home": 0, "away": 1}, "score": {"halftime": {"home": 0, "away": 0}, "fulltime": {"home": 0, "away": 1}, "extratime": {"home": null, "away": null}, "penalty": {"home": null, "away": null}}}, {"fixture": {"id": 244642, "referee": "Ahmed Ghandour", "timezone": "UTC", "date": "2019-12-24T17:30:00+00:00", "timestamp": 1577208600, "periods": {"first": 1577208600, "second": 1577212200}, "venue": {"id": 10635, "name": "WE Al-Ahly Stadium", "city": "Cairo"}, "status": {"long": "Match Finished", "short": "FT", "elapsed": 90}}, "league": {"id": 233, "name": "Premier League", "country": "Egypt", "logo": "https://media.api-sports.io/football/leagues/233.png", "flag": "https://media.api-sports.io/flags/eg.svg", "season": 2019, "round": "Regular Season - 10"}, "teams": {"home": {"id": 1034, "name": "El Entag EL Harby", "logo": "https://media.api-sports.io/football/teams/1034.png", "winner": null}, "away": {"id": 1040, "name": "Zamalek SC", "logo": "https://media.api-sports.io/football/teams/1040.png", "winner": null}}, "goals": {"home": 0, "away": 0}, "score": {"halftime": {"home": 0, "away": 0}, "fulltime": {"home": 0, "away": 0}, "extratime": {"home": null, "away": null}, "penalty": {"home": null, "away": null}}}, {"fixture": {"id": 179368, "referee": "L. Liani", "timezone": "UTC", "date": "2019-12-24T18:15:00+00:00", "timestamp": 1577211300, "periods": {"first": 1577211300, "second": 1577214900}, "venue": {"id": 868, "name": "Sammy Ofer Stadium", "city": "Haifa"}, "status": {"long": "Match Finished", "short": "FT", "elapsed": 90}}, "league": {"id": 383, "name": "Ligat Ha'al", "country": "Israel", "logo": "https://media.api-sports.io/football/leagues/383.png", "flag": "https://media.api-sports.io/flags/il.svg", "season": 2019, "round": "Regular Season - 15"}, "teams": {"home": {"id": 4195, "name": "Maccabi Haifa", "logo": "https://media.api-sports.io/football/teams/4195.png", "winner": true}, "away": {"id": 2253, "name": "Hapoel Haifa", "logo": "https://media.api-sports.io/football/teams/2253.png", "winner": false}}, "goals": {"home": 3, "away": 0}, "score": {"halftime": {"home": 0, "away": 0}, "fulltime": {"home": 3, "away": 0}, "extratime": {"home": null, "away": null}, "penalty": {"home": null, "away": null}}}, {"fixture": {"id": 179370, "referee": "I. Frid", "timezone": "UTC", "date": "2019-12-24T18:15:00+00:00", "timestamp": 1577211300, "periods": {"first": 1577211300, "second": 1577214900}, "venue": {"id": 10592, "name": "Bloomfield Stadium", "city": "Tel-Aviv"}, "status": {"long": "Match Finished", "short": "FT", "elapsed": 90}}, "league": {"id": 383, "name": "Ligat Ha'al", "country": "Israel", "logo": "https://media.api-sports.io/football/leagues/383.png", "flag": "https://media.api-sports.io/flags/il.svg", "season": 2019, "round": "Regular Season - 15"}, "teams": {"home": {"id": 4508, "name": "Bnei Yehuda", "logo": "https://media.api-sports.io/football/teams/4508.png", "winner": false}, "away": {"id": 604, "name": "Maccabi Tel Aviv", "logo": "https://media.api-sports.io/football/teams/604.png", "winner": true}}, "goals": {"home": 0, "away": 3}, "score": {"halftime": {"home": 0, "away": 2}, "fulltime": {"home": 0, "away": 3}, "extratime": {"home": null, "away": null}, "penalty": {"home": null, "away": null}}}, {"fixture": {"id": 292956, "referee": null, "timezone": "UTC", "date": "2019-12-24T23:00:00+00:00", "timestamp": 1577228400, "periods": {"first": 1577228400, "second": 1577232000}, "venue": {"id": null, "name": null, "city": null}, "status": {"long": "Match Finished", "short": "FT", "elapsed": 90}}, "league": {"id": 378, "name": "Ligue 1", "country": "Guinea", "logo": "https://media.api-sports.io/football/leagues/378.png", "flag": "https://media.api-sports.io/flags/gn.svg", "season": 2019, "round": "Regular Season - 5"}, "teams": {"home": {"id": 4420, "name": "Santoba", "logo": "https://media.api-sports.io/football/teams/4420.png", "winner": true}, "away": {"id": 4409, "name": "ASFAG", "logo": "https://media.api-sports.io/football/teams/4409.png", "winner": false}}, "goals": {"home": 2, "away": 1}, "score": {"halftime": {"home": null, "away": null}, "fulltime": {"home": 2, "away": 1}, "extratime": {"home": null, "away": null}, "penalty": {"home": null, "away": null}}}]}